examples/__init__.py
examples/eventsprofiles_btyd.py
examples/eventsprofiles_datamodel.py
neural_lifetimes/__init__.py
neural_lifetimes/inference.py
neural_lifetimes/run_model.py
neural_lifetimes/data/__init__.py
neural_lifetimes/data/utils.py
neural_lifetimes/data/dataloaders/__init__.py
neural_lifetimes/data/dataloaders/sequence_loader.py
neural_lifetimes/data/datamodules/__init__.py
neural_lifetimes/data/datamodules/sequence_datamodule.py
neural_lifetimes/data/datasets/__init__.py
neural_lifetimes/data/datasets/btyd.py
neural_lifetimes/data/datasets/clickhouse_sequence.py
neural_lifetimes/data/datasets/pandas_dataset.py
neural_lifetimes/data/datasets/sequence_dataset.py
neural_lifetimes/losses/__init__.py
neural_lifetimes/losses/distributional_losses.py
neural_lifetimes/metrics/__init__.py
neural_lifetimes/metrics/kullback_leibler.py
neural_lifetimes/metrics/sinkhorn.py
neural_lifetimes/models/__init__.py
neural_lifetimes/models/modules/__init__.py
neural_lifetimes/models/modules/classic_model.py
neural_lifetimes/models/modules/configure_optimizers.py
neural_lifetimes/models/nets/__init__.py
neural_lifetimes/models/nets/custom_par.py
neural_lifetimes/models/nets/custom_tvae.py
neural_lifetimes/models/nets/embedder.py
neural_lifetimes/models/nets/encoder_decoder.py
neural_lifetimes/models/nets/event_model.py
neural_lifetimes/models/nets/heads.py
neural_lifetimes/models/nets/mlp.py
neural_lifetimes/utils/__init__.py
neural_lifetimes/utils/date_arithmetic.py
neural_lifetimes/utils/aws/__init__.py
neural_lifetimes/utils/aws/query.py
neural_lifetimes/utils/aws/s3_utils.py
neural_lifetimes/utils/aws/utils.py
neural_lifetimes/utils/callbacks/__init__.py
neural_lifetimes/utils/callbacks/churn_monitor.py
neural_lifetimes/utils/callbacks/distribution_monitor.py
neural_lifetimes/utils/callbacks/get_tensorboard_logger.py
neural_lifetimes/utils/callbacks/git.py
neural_lifetimes/utils/callbacks/projection_monitor.py
neural_lifetimes/utils/clickhouse/__init__.py
neural_lifetimes-0.1.0.dist-info/LICENSE
neural_lifetimes-0.1.0.dist-info/METADATA
neural_lifetimes-0.1.0.dist-info/WHEEL
neural_lifetimes-0.1.0.dist-info/top_level.txt
neural_lifetimes-0.1.0.dist-info/RECORD
