Metadata-Version: 2.1
Name: neural-lifetimes
Version: 0.1.0
Summary: User behavior prediction from event data.
Home-page: https://github.com/transferwise/neural_lifetimes
Author: Wise
Classifier: License :: OSI Approved :: Apache Software License
Classifier: Programming Language :: Python :: 3 :: Only
Classifier: Programming Language :: Python :: 3.8
Classifier: Programming Language :: Python :: 3.9
License-File: LICENSE
Requires-Dist: boto3 (~=1.17)
Requires-Dist: botocore (~=1.20)
Requires-Dist: clickhouse-driver (~=0.2.4)
Requires-Dist: cloudpickle (~=2.0)
Requires-Dist: ctgan (~=0.5.1)
Requires-Dist: deepecho (~=0.3.0.post1)
Requires-Dist: matplotlib (~=3.5)
Requires-Dist: numpy (~=1.21)
Requires-Dist: pandas (~=1.1)
Requires-Dist: pyarrow (~=7.0)
Requires-Dist: torch (~=1.11)
Requires-Dist: pytorch-lightning (~=1.6)
Requires-Dist: rdt (~=0.6.3)
Requires-Dist: scikit-learn (~=1.0)
Requires-Dist: scipy (~=1.6)
Requires-Dist: sdv (~=0.13.1)
Requires-Dist: SQLAlchemy (~=1.3.24)
Requires-Dist: torchmetrics (~=0.8)
Requires-Dist: tqdm (~=4.64)
Requires-Dist: vaex (~=4.7)
Requires-Dist: plotly (~=5.7)
Provides-Extra: test
Requires-Dist: black (==22.3.0) ; extra == 'test'
Requires-Dist: click (==8.0.4) ; extra == 'test'
Requires-Dist: flake8 (==4.0.1) ; extra == 'test'
Requires-Dist: flake8-docstrings (==1.6.0) ; extra == 'test'
Requires-Dist: nbsphinx (==0.8.8) ; extra == 'test'
Requires-Dist: nbsphinx-link (==1.3.0) ; extra == 'test'
Requires-Dist: pytest (==6.2.5) ; extra == 'test'
Requires-Dist: pytest-cov (==3.0.0) ; extra == 'test'
Requires-Dist: python-snappy (==0.6.1) ; extra == 'test'
Requires-Dist: sphinx (==4.3.2) ; extra == 'test'
Requires-Dist: sphinx-rtd-theme (==1.0.0) ; extra == 'test'
